rensai/__init__.py
rensai-0.0.0.dist-info/LICENSE
rensai-0.0.0.dist-info/WHEEL
rensai-0.0.0.dist-info/METADATA
rensai-0.0.0.dist-info/RECORD
