Metadata-Version: 2.1
Name: rensai
Version: 0.0.0
Summary: Serialization framework for Python.
Home-page: https://github.com/nekitdev/rensai
License: MIT
Keywords: python,singleton
Author: nekitdev
Requires-Python: >=3.7
Classifier: Development Status :: 5 - Production/Stable
Classifier: Intended Audience :: Developers
Classifier: License :: OSI Approved :: MIT License
Classifier: Operating System :: OS Independent
Classifier: Programming Language :: Python :: 3
Classifier: Programming Language :: Python :: 3.7
Classifier: Programming Language :: Python :: 3.8
Classifier: Programming Language :: Python :: 3.9
Classifier: Programming Language :: Python :: 3.10
Classifier: Programming Language :: Python :: 3.11
Classifier: Topic :: Utilities
Classifier: Typing :: Typed
Requires-Dist: named (>=1.1.0)
Project-URL: Documentation, https://nekitdev.github.io/rensai
Project-URL: Discord, https://nekit.dev/discord
Project-URL: Funding, https://patreon.com/nekitdev
Project-URL: Issues, https://github.com/nekitdev/rensai/issues
Project-URL: Repository, https://github.com/nekitdev/rensai
